babachi/__init__.py
babachi/__main__.py
babachi/bad_estimation.py
babachi/chrom_wrapper.py
babachi/helpers.py
babachi/logging.py
babachi/models.py
babachi/segmentation.py
babachi/stats.py
babachi/validators.py
babachi/version.py
babachi/visualize_segmentation.py
babachi/tests/test.bed
babachi-3.0.0.dist-info/METADATA
babachi-3.0.0.dist-info/WHEEL
babachi-3.0.0.dist-info/entry_points.txt
babachi-3.0.0.dist-info/top_level.txt
babachi-3.0.0.dist-info/RECORD
