Metadata-Version: 2.4
Name: babachi
Version: 3.0.0
Home-page: https://github.com/autosome-ru/BABACHI
Author: Sergey Abramov, Alexandr Boytsov
Author-email: sabramov@altius.org
Requires-Python: >=3.6
Requires-Dist: docopt>=0.6.2
Requires-Dist: numpy<2.0,>=1.19.5
Requires-Dist: schema>=0.7.2
Requires-Dist: contextlib2>=0.5.5
Requires-Dist: pandas>=1.0.4
Requires-Dist: matplotlib>=3.2.1
Requires-Dist: seaborn>=0.10.1
Requires-Dist: numba>=0.53.1
Requires-Dist: pysam>=0.13.4
Requires-Dist: scipy>=1.5.1
Requires-Dist: validators>=0.18.2
Provides-Extra: dev
Requires-Dist: wheel; extra == "dev"
Requires-Dist: twine; extra == "dev"
Requires-Dist: setuptools_scm; extra == "dev"
Provides-Extra: vcf
Requires-Dist: pysam; extra == "vcf"
Dynamic: author
Dynamic: author-email
Dynamic: description
Dynamic: home-page
Dynamic: provides-extra
Dynamic: requires-dist
Dynamic: requires-python
